Workbook

Sheet INVOICE
A1: COMMERCIAL INVOICE
A2: Shipper/Exporter | E2: No. & Date of Invoice
A3: HongKong Hope Sun Industrial Limited | E3: Invoice No | F3: NT251209001
A4: No. A1, Room 1501, Grand Millennium Plaza, 181 Queen’s Road Central, Hongkong | E4: Invoice Date: | F4: 46000
A7: Bill To: | E7: Payment Term
A8: Sernet (Suzhou) Technologies Corporation
A9: No.8,Tangzhuang Road, Suzhou Industrial Park, Jiangsu, China
A11: Ship To: | E11: Trade Term
A12: Sernet (Suzhou) Technologies Corporation | E12: DDP
A13: No.8,Tangzhuang Road, Suzhou Industrial Park, Jiangsu, China
A14: Port of Loading | C14: Port of Discharge | E14: Remarks:
A17: Carrier | C17: Sailing on/or About
E18: 贸易国： | F18: 中国香港
A19: ITEM | B19: Part No. | C19: PO No. | D19: Description of Goods | E19: Quantity | F19: Unit | G19: Unit Price | H19: Currency | I19: Amount | J19: COO | K19: COD | L19: 品牌 | M19: 品牌类型 | N19: 型号 | O19: Net WT(KGS)
A20: 1 | B20: 942CQK14KP | C20: 2251002417 | D20: 外壳 | E20: 4800 | F20: PCS | G20: 4.656 | H20: USD | I20: =ROUND(E20*G20,2) -> 22348.8 | J20: CN | L20: 无品牌 | M20: 无品牌 | N20: 无型号 | O20: 2043.84
C27: TOTAL | E27: =SUM(E20:E26) -> 4800 | I27: =SUM(I20:I26) -> 22348.8 | O27: =SUM(O20:O26) -> 2043.84
A29: 1 | B29: 进境口岸关别代码 | D29: 南通综保（2376）
A30: 2 | B30: 申报地口岸关别代码 | D30: 南通综保（2376）
A31: 3 | B31: 报关行名称及代码 | D31: 南通煦伟国际货运代理有限公司 3206980081，91320600MA1MH7FP0H
A32: 4 | B32: 关联手册（账册）编码 | D32: T2376W000083
A33: 5 | B33: 运输方式 | D33: 保税港区

Sheet PACKING
A1: PACKING LIST
A3: Shipper/Exporter | E3: No & Date of Invoice
A4: =INVOICE!A3 -> HongKong Hope Sun Industrial Limited | E4: =INVOICE!E3 -> Invoice No | F4: =INVOICE!F3 -> NT251209001
A5: =INVOICE!A4 -> No. A1, Room 1501, Grand Millennium Plaza, 181 Queen’s Road Central, Hongkong | E5: =INVOICE!E4 -> Invoice Date: | F5: =INVOICE!F4 -> 46000
A8: Bill To: | E8: Remarks:
A9: =INVOICE!A8 -> Sernet (Suzhou) Technologies Corporation
A10: =INVOICE!A9 -> No.8,Tangzhuang Road, Suzhou Industrial Park, Jiangsu, China
A13: Ship To:
A14: =INVOICE!A12 -> Sernet (Suzhou) Technologies Corporation
A15: =INVOICE!A13 -> No.8,Tangzhuang Road, Suzhou Industrial Park, Jiangsu, China
A17: Port of Departure | D17: Port of Arrival
A19: Carrier | D19: Sailing on/or About
A21: CTNS | B21: PO No. | C21: Part No. | D21: Description of Goods | E21: Quantity | F21: Unit | G21: Net WT | H21: Gross WT | I21: MEASUREMENT L*W*H(CM)
G22: KGS | H22: KGS
A23: 300 | B23: =INVOICE!C20 -> 2251002417 | C23: =INVOICE!B20 -> 942CQK14KP | D23: =INVOICE!D20 -> 外壳 | E23: =INVOICE!E20 -> 4800 | F23: =INVOICE!F20 -> PCS | G23: =INVOICE!O20 -> 2043.84 | H23: 2707.5 | I23: 57.5*39*25
A30: =SUM(A23:A29) -> 300 | E30: =SUM(E23:E29) -> 4800 | G30: =SUM(G23:G29) -> 2043.84 | H30: =SUM(H23:H29) -> 2707.5
E31: 300（300胶框）
E32: 胶框
