Workbook

Sheet INVOICE
A1: COMMERCIAL INVOICE
A2: Shipper/Exporter | E2: No. & Date of Invoice
A3: HongKong Hope Sun Industrial Limited | E3: Invoice No | F3: NT251212001
A4: No. A1, Room 1501, Grand Millennium Plaza, 181 Queen’s Road Central, Hongkong | E4: Invoice Date: | F4: 46003
A7: Bill To: | E7: Payment Term
A8: Sernet (Suzhou) Technologies Corporation
A9: No.8,Tangzhuang Road, Suzhou Industrial Park, Jiangsu, China
A11: Ship To: | E11: Trade Term
A12: Sernet (Suzhou) Technologies Corporation | E12: DDP
A13: No.8,Tangzhuang Road, Suzhou Industrial Park, Jiangsu, China
A14: Port of Loading | C14: Port of Discharge | E14: Remarks:
A17: Carrier | C17: Sailing on/or About
E18: 贸易国： | F18: 中国香港
A19: ITEM | B19: Part No. | C19: PO No. | D19: Description of Goods | E19: Quantity | F19: Unit | G19: Unit Price | H19: Currency | I19: Amount | J19: COO | K19: COD | L19: 品牌 | M19: 品牌类型 | N19: 型号 | O19: Net WT(KGS)
A20: 1 | B20: 942DE203KP | C20: 2250901366 | D20: 下盖组件 | E20: 440 | F20: SET | G20: 10.8388 | H20: USD | I20: =ROUND(E20*G20,2) -> 4769.07 | J20: CN | L20: 无品牌 | M20: 无品牌 | N20: 无型号 | O20: 575.39
A21: 2 | B21: 942DE203KP | C21: 2250901366 | D21: 下盖组件 | E21: 200 | F21: SET | G21: 10.8388 | H21: USD | I21: =ROUND(E21*G21,2) -> 2167.76 | J21: CN | L21: 无品牌 | M21: 无品牌 | N21: 无型号 | O21: 261.54
A22: 3 | B22: 942DE221KP | C22: 2250903224 | D22: 支架 | E22: 720 | F22: PCS | G22: 1.7654 | H22: USD | I22: =ROUND(E22*G22,2) -> 1271.09 | J22: CN | L22: 无品牌 | M22: 无品牌 | N22: 无型号 | O22: 67.68
A23: 4 | B23: 942CQK14KP | C23: 2251002417 | D23: 外壳 | E23: 320 | F23: PCS | G23: 4.656 | H23: USD | I23: =ROUND(E23*G23,2) -> 1489.92 | J23: CN | L23: 无品牌 | M23: 无品牌 | N23: 无型号 | O23: 136.26
A24: 5 | B24: 942DB104KP | C24: 2251102591 | D24: 外壳 | E24: 4080 | F24: PCS | G24: 3.589 | H24: USD | I24: =ROUND(E24*G24,2) -> 14643.12 | J24: CN | L24: 无品牌 | M24: 无品牌 | N24: 无型号 | O24: 948.19
A25: 6 | B25: 942DKS03KP | C25: 2250802780 | D25: 外壳 | E25: 104 | F25: PCS | G25: 6.4311 | H25: USD | I25: =ROUND(E25*G25,2) -> 668.83 | J25: CN | L25: 无品牌 | M25: 无品牌 | N25: 无型号 | O25: 72.28
A26: 7 | B26: 942DKS03KP | C26: 2250903224 | D26: 外壳 | E26: 1496 | F26: PCS | G26: 6.4311 | H26: USD | I26: =ROUND(E26*G26,2) -> 9620.93 | J26: CN | L26: 无品牌 | M26: 无品牌 | N26: 无型号 | O26: 1039.72
C27: TOTAL | E27: =SUM(E20:E26) -> 7360 | I27: =SUM(I20:I26) -> 34630.72 | O27: =SUM(O20:O26) -> 3101.06
A29: 1 | B29: 进境口岸关别代码 | D29: 南通综保（2376）
A30: 2 | B30: 申报地口岸关别代码 | D30: 南通综保（2376）
A31: 3 | B31: 报关行名称及代码 | D31: 南通煦伟国际货运代理有限公司 3206980081，91320600MA1MH7FP0H
A32: 4 | B32: 关联手册（账册）编码 | D32: T2376W000083
A33: 5 | B33: 运输方式 | D33: 保税港区

Sheet PACKING
A1: PACKING LIST
A3: Shipper/Exporter | E3: No & Date of Invoice
A4: =INVOICE!A3 -> HongKong Hope Sun Industrial Limited | E4: =INVOICE!E3 -> Invoice No | F4: =INVOICE!F3 -> NT251212001
A5: =INVOICE!A4 -> No. A1, Room 1501, Grand Millennium Plaza, 181 Queen’s Road Central, Hongkong | E5: =INVOICE!E4 -> Invoice Date: | F5: =INVOICE!F4 -> 46003
A8: Bill To: | E8: Remarks:
A9: =INVOICE!A8 -> Sernet (Suzhou) Technologies Corporation
A10: =INVOICE!A9 -> No.8,Tangzhuang Road, Suzhou Industrial Park, Jiangsu, China
A13: Ship To:
A14: =INVOICE!A12 -> Sernet (Suzhou) Technologies Corporation
A15: =INVOICE!A13 -> No.8,Tangzhuang Road, Suzhou Industrial Park, Jiangsu, China
A17: Port of Departure | D17: Port of Arrival
A19: Carrier | D19: Sailing on/or About
A21: CTNS | B21: PO No. | C21: Part No. | D21: Description of Goods | E21: Quantity | F21: Unit | G21: Net WT | H21: Gross WT | I21: MEASUREMENT L*W*H(CM)
G22: KGS | H22: KGS
A23: 55 | B23: 2250901366 | C23: 942DE203KP | D23: 下盖组件 | E23: =INVOICE!E20 -> 440 | F23: =INVOICE!F20 -> SET | G23: =INVOICE!O20 -> 575.39 | H23: 630.3 | I23: 61*32*24
A24: 25 | B24: 2250901366 | C24: 942DE203KP | D24: 下盖组件 | E24: =INVOICE!E21 -> 200 | F24: =INVOICE!F21 -> SET | G24: =INVOICE!O21 -> 261.54 | H24: 286.5 | I24: 61*32*24
A25: 12 | B25: 2250903224 | C25: 942DE221KP | D25: 支架 | E25: =INVOICE!E22 -> 720 | F25: =INVOICE!F22 -> PCS | G25: =INVOICE!O22 -> 67.68 | H25: 84.288 | I25: 52.3*44.8*20
A26: 20 | B26: 2251002417 | C26: 942CQK14KP | D26: 外壳 | E26: =INVOICE!E23 -> 320 | F26: =INVOICE!F23 -> PCS | G26: =INVOICE!O23 -> 136.26 | H26: 180.5 | I26: 57.5*39*25
A27: 136 | B27: 2251102591 | C27: 942DB104KP | D27: 外壳 | E27: =INVOICE!E24 -> 4080 | F27: =INVOICE!F24 -> PCS | G27: =INVOICE!O24 -> 948.19 | H27: 1254.6 | I27: 30*24*20.5
A28: 7 | B28: 2250802780 | C28: 942DKS03KP | D28: 外壳 | E28: =INVOICE!E25 -> 104 | F28: =INVOICE!F25 -> PCS | G28: =INVOICE!O25 -> 72.28 | H28: 87.1975 | I28: 57.5*39*25
A29: 93 | B29: 2250903224 | C29: 942DKS03KP | D29: 外壳 | E29: =INVOICE!E26 -> 1496 | F29: =INVOICE!F26 -> PCS | G29: =INVOICE!O26 -> 1039.72 | H29: 1254.3025 | I29: 57.5*39*25
A30: =SUM(A23:A29) -> 348 | E30: =SUM(E23:E29) -> 7360 | G30: =SUM(G23:G29) -> 3101.06 | H30: =SUM(H23:H29) -> 3777.688
E31: 348（256胶框+92纸箱）
E32: 胶框+纸箱
