Workbook

Sheet INVOICE
A1: COMMERCIAL INVOICE
A2: Shipper/Exporter | E2: No. & Date of Invoice
A3: SHANGHAI JIAN SAN ELECTRONICS CO., LTD. | E3: 45880
A4: 上海健三电子有限公司 | E4: JS250801562
A6: Bill To: | B6: 买方 | E6: Payment Term
A7: Sernet(Suzhou)Technologies Corporation | E7: 月结30天+4个月贴息
A8: 中磊电子（苏州）有限公司 No.8,Tangzhuang Road, Suzhou Industrial Park, Jiangsu, China
A10: Ship To: | E10: Trade Term
A11: 苏州工业园区唐庄路8号 | E11: CIF SH
A12: No.8,Tangzhuang Road, Suzhou Industrial Park, Jiangsu, China
A13: Port of Loading | C13: Port of Discharge | E13: Remarks:
A16: Carrier | C16: Sailing on/or About
E17: 贸易国： | F17: 中国
A18: ITEM | B18: Part No. | C18: PO No. | D18: Description of Goods | E18: Quantity | F18: Unit | G18: Unit Price | H18: Currency | I18: Amount | J18: COO | K18: COD | L18: 品牌 | M18: 品牌类型 | N18: 型号 | O18: Net WT(KGS)
A19: 1 | B19: 36030205MU | C19: 2250402112 | D19: 电感器 | E19: 10000 | F19: PCS | G19: 0.0026 | H19: USD | I19: 26 | J19: Japan | L19: Murata 村田 | M19: 境外品牌（其他） | N19: LQG15HN3N0S02D | O19: 0.01 | Q19: =VLOOKUP(J19,[1]国家代码!$A$1:$B$65536,2,0) -> 116
A20: 2 | B20: 3601021AMU | C20: 2250501401 | D20: 电感器 | E20: 10000 | F20: PCS | G20: 0.0134 | H20: USD | I20: 134 | J20: Japan | L20: Murata 村田 | M20: 境外品牌（其他） | N20: LQG15HS1N0B02D | O20: 0.008 | Q20: =VLOOKUP(J20,[1]国家代码!$A$1:$B$65536,2,0) -> 116
A21: 3 | B21: 3602231GMU | C21: 2250401363 | D21: 电感器 | E21: 20000 | F21: PCS | G21: 0.00216 | H21: USD | I21: 43.2 | J21: Japan | L21: Murata 村田 | M21: 境外品牌（其他） | N21: LQG15HS22NJ02D | O21: 0.02 | Q21: =VLOOKUP(J21,[1]国家代码!$A$1:$B$65536,2,0) -> 116
A22: 4 | B22: 3604755XMU | C22: 2250402112 | D22: 电感器 | E22: 8000 | F22: PCS | G22: 0.035 | H22: USD | I22: 280 | J22: Japan | L22: Murata 村田 | M22: 境外品牌（其他） | N22: LQM21PN4R7MGRD | O22: 0.096 | Q22: =VLOOKUP(J22,[1]国家代码!$A$1:$B$65536,2,0) -> 116
A23: 5 | B23: 3602253QMU | C23: 2250303958 | D23: 电感器 | E23: 9000 | F23: PCS | G23: 0.047 | H23: USD | I23: 423 | J23: Japan | L23: Murata 村田 | M23: 境外品牌（其他） | N23: LQM2MPN2R2MEHL | O23: 0.041 | Q23: =VLOOKUP(J23,[1]国家代码!$A$1:$B$65536,2,0) -> 116
A24: 6 | B24: 3602253QMU | C24: 2250402932 | D24: 电感器 | E24: 3000 | F24: PCS | G24: 0.047 | H24: USD | I24: 141 | J24: Japan | L24: Murata 村田 | M24: 境外品牌（其他） | N24: LQM2MPN2R2MEHL | O24: 0.013 | Q24: =VLOOKUP(J24,[1]国家代码!$A$1:$B$65536,2,0) -> 116
A25: 7 | B25: 3602253QMU | C25: 2250500241 | D25: 电感器 | E25: 3000 | F25: PCS | G25: 0.047 | H25: USD | I25: 141 | J25: Japan | L25: Murata 村田 | M25: 境外品牌（其他） | N25: LQM2MPN2R2MEHL | O25: 0.013 | Q25: =VLOOKUP(J25,[1]国家代码!$A$1:$B$65536,2,0) -> 116
A26: 8 | B26: 3601621HMU | C26: 2250703086 | D26: 电感器 | E26: 15000 | F26: PCS | G26: 0.0091 | H26: USD | I26: 136.5 | J26: Japan | L26: Murata 村田 | M26: 境外品牌（其他） | N26: LQP03HQ1N6W02D | O26: 0.003 | Q26: =VLOOKUP(J26,[1]国家代码!$A$1:$B$65536,2,0) -> 116
A27: 9 | B27: 3601720AMU | C27: 2250703086 | D27: 电感器 | E27: 15000 | F27: PCS | G27: 0.0091 | H27: USD | I27: 136.5 | J27: Japan | L27: Murata 村田 | M27: 境外品牌（其他） | N27: LQP03HQ1N7W02D | O27: 0.003 | Q27: =VLOOKUP(J27,[1]国家代码!$A$1:$B$65536,2,0) -> 116
A28: 10 | B28: 3603322NMU | C28: 2250401274 | D28: 电感器 | E28: 30000 | F28: PCS | G28: 0.0078 | H28: USD | I28: 234 | J28: Japan | L28: Murata 村田 | M28: 境外品牌（其他） | N28: LQP03PN3N3C02D | O28: 0.005 | Q28: =VLOOKUP(J28,[1]国家代码!$A$1:$B$65536,2,0) -> 116
A29: 11 | B29: 3604722SMU | C29: 2250500241 | D29: 电感器 | E29: 15000 | F29: PCS | G29: 0.0078 | H29: USD | I29: 117 | J29: Japan | L29: Murata 村田 | M29: 境外品牌（其他） | N29: LQP03PN4N7J02D | O29: 0.005 | Q29: =VLOOKUP(J29,[1]国家代码!$A$1:$B$65536,2,0) -> 116
A30: 12 | B30: 36050102MU | C30: 2250400172 | D30: 电感器 | E30: 15000 | F30: PCS | G30: 0.00175 | H30: USD | I30: 26.25 | J30: Japan | L30: Murata 村田 | M30: 境外品牌（其他） | N30: LQP03TG0N5B02D | O30: 0.011 | Q30: =VLOOKUP(J30,[1]国家代码!$A$1:$B$65536,2,0) -> 116
... A83: 65 | B83: 55215241MU0 | C83: 2250201245 | D83: 双工器 | E83: 10000 | F83: PCS | G83: 0.014 | H83: USD | I83: 140 | J83: Japan | L83: Murata 村田 | M83: 境外品牌（其他） | N83: LFD152G45MU6E208 | O83: 0.004 | Q83: =VLOOKUP(J83,[1]国家代码!$A$1:$B$65536,2,0) -> 116
C85: TOTAL | E85: 1109000 | I85: 7810.3 | O85: 1.955
A87: 1.进境口岸关别代码：外高桥关（2218）
A88: 2.申报地口岸关别代码 ：外高桥关（2218）
A89: 3.报关行名称及代码 ：上海鸣旌国际物流有限公司（312248011T）
A90: 4.关联手册(账册）编号 ：T2218W002877 | D90: 多元账号 | E90: 金二账册号：T2218W002877
A91: 5.贸易国 :中国
A92: 6.包装种类 ：纸箱
A93: 7.运输方式：保税区

Sheet PACKING
A1: PACKING LIST
A3: Shipper/Exporter | F3: No & Date of Invoice
A4: SHANGHAI JIAN SAN ELECTRONICS CO., LTD. | F4: 45880
A5: 上海健三电子有限公司Room301, 3rd floor, Section South, Buliding 1, No.24, Jiafeng Road, China(Shanghai) Free Trade Zone | F5: JS250801562
A8: Bill To: | F8: Remarks:
A9: Sernet(Suzhou)Technologies Corporation
A10: 中磊电子（苏州）有限公司 No.8,Tangzhuang Road, Suzhou Industrial Park, Jiangsu, China
A13: Ship To:
A14: 苏州工业园区唐庄路8号
A15: No.8,Tangzhuang Road, Suzhou Industrial Park, Jiangsu, China
A17: Port of Departure | D17: Port of Arrival
A19: Carrier | D19: Sailing on/or About
A21: CTNS | B21: PO No. | C21: Part No. | D21: Description of Goods | F21: Quantity | G21: Unit | H21: Net WT | I21: Gross WT | J21: MEASUREMENT L*W*H(CM) | K21: 型号
H22: KGS | I22: KGS | L22: MOQ | N22: 汇总净重 | O22: 汇总数量
A23: C/N01-01# | B23: 2250402112 | C23: 36030205MU | D23: 电感器 | F23: 10000 | G23: PCS | H23: 0.01 | I23: 0.15 | J23: 50*40*20 | K23: LQG15HN3N0S02D | L23: 10000 | M23: 1 | N23: 0.01 | O23: 10000 | P23: 0 | Q23: 0.14 | R23: Japan
A24: C/N01-01# | B24: 2250501401 | C24: 3601021AMU | D24: 电感器 | F24: 10000 | G24: PCS | H24: 0.008 | I24: 0.15 | J24: 50*40*20 | K24: LQG15HS1N0B02D | L24: 10000 | M24: 1 | N24: 0.008 | O24: 10000 | P24: 0 | Q24: 0.142 | R24: Japan
A25: C/N01-01# | B25: 2250401363 | C25: 3602231GMU | D25: 电感器 | F25: 20000 | G25: PCS | H25: 0.02 | I25: 0.3 | J25: 50*40*20 | K25: LQG15HS22NJ02D | L25: 10000 | M25: 2 | N25: 0.02 | O25: 20000 | P25: 0 | Q25: 0.28 | R25: Japan
A26: C/N01-01# | B26: 2250402112 | C26: 3604755XMU | D26: 电感器 | F26: 8000 | G26: PCS | H26: 0.096 | I26: 0.3 | J26: 50*40*20 | K26: LQM21PN4R7MGRD | L26: 4000 | M26: 2 | N26: 0.096 | O26: 8000 | P26: 0 | Q26: 0.204 | R26: Japan
A27: C/N01-01# | B27: 2250303958 | C27: 3602253QMU | D27: 电感器 | F27: 9000 | G27: PCS | H27: 0.041 | I27: 0.45 | J27: 50*40*20 | K27: LQM2MPN2R2MEHL | L27: 3000 | M27: 3 | N27: 0.067 | O27: 15000 | P27: -6000 | Q27: 0.409 | R27: Japan
A28: C/N01-01# | B28: 2250402932 | C28: 3602253QMU | D28: 电感器 | F28: 3000 | G28: PCS | H28: 0.013 | I28: 0.15 | J28: 50*40*20 | K28: LQM2MPN2R2MEHL | L28: 3000 | M28: 1 | N28: 0.067 | O28: 15000 | P28: -12000 | Q28: 0.137 | R28: Japan
A29: C/N01-01# | B29: 2250500241 | C29: 3602253QMU | D29: 电感器 | F29: 3000 | G29: PCS | H29: 0.013 | I29: 0.15 | J29: 50*40*20 | K29: LQM2MPN2R2MEHL | L29: 3000 | M29: 1 | N29: 0.067 | O29: 15000 | P29: -12000 | Q29: 0.137 | R29: Japan
A30: C/N01-01# | B30: 2250703086 | C30: 3601621HMU | D30: 电感器 | F30: 15000 | G30: PCS | H30: 0.003 | I30: 0.15 | J30: 50*40*20 | K30: LQP03HQ1N6W02D | L30: 15000 | M30: 1 | N30: 0.003 | O30: 15000 | P30: 0 | Q30: 0.147 | R30: Japan
A31: C/N01-01# | B31: 2250703086 | C31: 3601720AMU | D31: 电感器 | F31: 15000 | G31: PCS | H31: 0.003 | I31: 0.15 | J31: 50*40*20 | K31: LQP03HQ1N7W02D | L31: 15000 | M31: 1 | N31: 0.003 | O31: 15000 | P31: 0 | Q31: 0.147 | R31: Japan
A32: C/N01-01# | B32: 2250401274 | C32: 3603322NMU | D32: 电感器 | F32: 30000 | G32: PCS | H32: 0.005 | I32: 0.3 | J32: 50*40*20 | K32: LQP03PN3N3C02D | L32: 15000 | M32: 2 | N32: 0.005 | O32: 30000 | P32: 0 | Q32: 0.295 | R32: Japan
A33: C/N01-01# | B33: 2250500241 | C33: 3604722SMU | D33: 电感器 | F33: 15000 | G33: PCS | H33: 0.005 | I33: 0.15 | J33: 50*40*20 | K33: LQP03PN4N7J02D | L33: 15000 | M33: 1 | N33: 0.005 | O33: 15000 | P33: 0 | Q33: 0.145 | R33: Japan
A34: C/N01-01# | B34: 2250400172 | C34: 36050102MU | D34: 电感器 | F34: 15000 | G34: PCS | H34: 0.011 | I34: 0.15 | J34: 50*40*20 | K34: LQP03TG0N5B02D | L34: 15000 | M34: 1 | N34: 0.022 | O34: 30000 | P34: -15000 | Q34: 0.139 | R34: Japan
... A87: C/N02-03# | B87: 2250201245 | C87: 55215241MU0 | D87: 双工器 | F87: 10000 | G87: PCS | H87: 0.004 | I87: 0.15 | J87: 50*40*20 | K87: LFD152G45MU6E208 | L87: 10000 | M87: 1 | N87: 0.004 | O87: 10000 | P87: 0 | Q87: 0.146 | R87: Japan
A88: C/N02-03#
A90: 3 | E90: TOTAL | F90: 1109000 | H90: 1.955 | I90: 15.6 | J90: 0.12m³
E91: 件数 | F91: 3 件
E92: 包装种类 | F92: 纸箱
E93: 托盘材质 | F93: 无
A97: 1.进境口岸关别代码：外高桥关（2218）
A98: 2.申报地口岸关别代码 ：外高桥关（2218）
A99: 3.报关行名称及代码 ：上海鸣旌国际物流有限公司（312248011T）
A100: 4.关联手册(账册）编号 ：T2218W002877 | D100: 多元账号 | E100: 金二账册号：T2218W002877
A101: 5.贸易国 :中国
A102: 6.包装种类 ：纸箱
