Workbook

Sheet Sheet1
A1: 产品购销合同
A2: 供 方：加高電子股份有限公司 | G2: 进料对口
A3: 需 方：中磊電子(蘇州)有限公司
A4: 合同号 : 同INVOICE NO.
A5: 一、产品名称、型号、数量及金额
A7: PO号 | B7: 品名及料号 | C7: 型號 | D7: 供應商料號 | E7: 单位 | F7: 数量 | G7: 单价 | H7: 金额 | I7: 币制 | J7: 淨重 | K7: 原產國
A8: 2250600556-2.1 | B8: 3711260HHM | C8: HSX321S | D8: X3S012000BC1HA-HU | E8: PCS | F8: 3000 | G8: 0.031 | H8: =F8*G8 -> 93 | I8: USD | J8: 0.15 | K8: CHINA
A9: 2250600556-2.1 | B9: 3711260HHM | C9: HSX321S | D9: X3S012000BC1HA-HU | E9: PCS | F9: 3000 | G9: 0.031 | H9: =F9*G9 -> 93 | I9: USD | J9: 0.15 | K9: CHINA
A10: 2250300844-10.1 | B10: 3712061GHM | C10: HSX321S | D10: X3S025000BC1HA-HZ | E10: PCS | F10: 12000 | G10: 0.028 | H10: =F10*G10 -> 336 | I10: USD | J10: 0.56 | K10: CHINA
A11: 2250302067-3.1 | B11: 3712061GHM | C11: HSX321S | D11: X3S025000BC1HA-HZ | E11: PCS | F11: 3000 | G11: 0.028 | H11: =F11*G11 -> 84 | I11: USD | J11: 0.14 | K11: CHINA
A12: 2250501304-3.5 | B12: 3713260UHM | C12: HSX321S | D12: X3S032000BC1HC-HZ | E12: PCS | F12: 9000 | G12: 0.028 | H12: =F12*G12 -> 252 | I12: USD | J12: 0.4 | K12: CHINA
A13: 2250102340-3.1 | B13: 37138008HM | C13: HSX221SA | D13: X2B038400BA1HA-HZ | E13: PCS | F13: 6000 | G13: 0.0385 | H13: =F13*G13 -> 231 | I13: USD | J13: 0.16 | K13: THAILAND
A14: 2250102513-1.1 | B14: 37138008HM | C14: HSX221SA | D14: X2B038400BA1HA-HZ | E14: PCS | F14: 3000 | G14: 0.0385 | H14: =F14*G14 -> 115.5 | I14: USD | J14: 0.08 | K14: THAILAND
A15: 2250102986-3.1 | B15: 37138008HM | C15: HSX221SA | D15: X2B038400BA1HA-HZ | E15: PCS | F15: 18000 | G15: 0.0385 | H15: =F15*G15 -> 693 | I15: USD | J15: 0.46 | K15: THAILAND
A16: 2250300844-11.1 | B16: 3714062EHM | C16: HSX321S | D16: X3S040000BF1HF-HZ | E16: PCS | F16: 9000 | G16: 0.031 | H16: =F16*G16 -> 279 | I16: USD | J16: 0.37 | K16: CHINA
A17: 2250302067-4.1 | B17: 3714062EHM | C17: HSX321S | D17: X3S040000BF1HF-HZ | E17: PCS | F17: 3000 | G17: 0.031 | H17: =F17*G17 -> 93 | I17: USD | J17: 0.13 | K17: CHINA
A18: 2250302882-5.1 | B18: 3715060GHM | C18: HSX321S | D18: X3S050000CJ1HA-HPZ | E18: PCS | F18: 12000 | G18: 0.0295 | H18: =F18*G18 -> 354 | I18: USD | J18: 0.51 | K18: CHINA
A19: 2250302882-5.1 | B19: 3715060GHM | C19: HSX321S | D19: X3S050000CJ1HA-HPZ | E19: PCS | F19: 3000 | G19: 0.0295 | H19: =F19*G19 -> 88.5 | I19: USD | J19: 0.13 | K19: CHINA
... A21: 2250702505-4.1 | B21: 3720001PDS | C21: DSB1612SDN | D21: 7EG03200A01 | E21: PCS | F21: 500 | G21: 0.35 | H21: =F21*G21 -> 175 | I21: USD | J21: 0.1 | K21: JAPAN
F22: =SUM(F8:F21) -> 90500 | H22: =SUM(H8:H21) -> 3064 | J22: =SUM(J8:J21) -> 3.6
A23: 二、交(提)货地点、方式：中磊電子(蘇州)有限公司
A24: 三、运输方式及到达站港口和费用负担： DAP
A25: 四、包装标准、包装物的供应与回收和费用负担：供方
A26: 五、验收标准、方法及提出议期限：1个月
A27: 六、交货日期： | B27: 45883
A28: 七、结算方式：TT90
A30: 供方： | D30: 需方:
A31: 单位名称：加高電子股份有限公司 | D31: 单位名称：中磊電子(蘇州)有限公司
A32: 单位地址：高雄市大寮區大發工業區華東路39號 | D32: 单位地址：蘇州工業園區唐莊路8號
A33: 电话：886-7-787-1555
A34: 传真：886-7-787-1557

Sheet INVOICE
A1: COMMERCIAL INVOICE
A2: Shipper/Exporter | E2: No. & Date of Invoice
A3: HARMONY ELECTRONICS CORP. | E3: SH1-P80326
A4: No.39, Huadong Rd., Daliao Dist., Dafa Industrial Park, KAOHSIUNG 831, TAIWAN,CHINA | E4: 45883
A7: Bill To: | E7: Payment Term
A8: Sernet(Suzhou)Technologies Corporation | E8: TT90DAYS
A9: 中磊电子（苏州）有限公司 No.8,Tangzhuang Road, Suzhou Industrial Park, Jiangsu, China
A11: Ship To: | E11: Trade Term
A12: SAME AS CONSIGNEE | E12: DAP
A14: Port of Loading | C14: Port of Discharge | E14: Remarks:
A17: Carrier | C17: Sailing on/or About
E18: 贸易国： | F18: TAIWAN,CHINA
A19: ITEM | B19: Part No. | C19: PO No. | D19: Description of Goods | E19: Quantity | F19: Unit | G19: Unit Price | H19: Currency | I19: Amount | J19: COO | K19: COD | L19: 品牌 | M19: 品牌类型 | N19: 型号
A20: 1 | B20: 3711260HHM | C20: 2250600556-2.1 | D20: X3S012000BC1HA-HU | E20: 3000 | F20: PCS | G20: 0.031 | H20: USD | I20: =ROUND(E20*G20,2) -> 93 | J20: CHINA | L20: HELE | M20: 境外品牌(其它) | N20: HSX321S
A21: 2 | B21: 3711260HHM | C21: 2250600556-2.1 | D21: X3S012000BC1HA-HU | E21: 3000 | F21: PCS | G21: 0.031 | H21: USD | I21: =ROUND(E21*G21,2) -> 93 | J21: CHINA | L21: HELE | M21: 境外品牌(其它) | N21: HSX321S
A22: 3 | B22: 3712061GHM | C22: 2250300844-10.1 | D22: X3S025000BC1HA-HZ | E22: 12000 | F22: PCS | G22: 0.028 | H22: USD | I22: =ROUND(E22*G22,2) -> 336 | J22: CHINA | L22: HELE | M22: 境外品牌(其它) | N22: HSX321S
A23: 4 | B23: 3712061GHM | C23: 2250302067-3.1 | D23: X3S025000BC1HA-HZ | E23: 3000 | F23: PCS | G23: 0.028 | H23: USD | I23: =ROUND(E23*G23,2) -> 84 | J23: CHINA | L23: HELE | M23: 境外品牌(其它) | N23: HSX321S
A24: 5 | B24: 3713260UHM | C24: 2250501304-3.5 | D24: X3S032000BC1HC-HZ | E24: 9000 | F24: PCS | G24: 0.028 | H24: USD | I24: =ROUND(E24*G24,2) -> 252 | J24: CHINA | L24: HELE | M24: 境外品牌(其它) | N24: HSX321S
A25: 6 | B25: 37138008HM | C25: 2250102340-3.1 | D25: X2B038400BA1HA-HZ | E25: 6000 | F25: PCS | G25: 0.0385 | H25: USD | I25: =ROUND(E25*G25,2) -> 231 | J25: THAILAND | L25: HELE | M25: 境外品牌(其它) | N25: HSX221SA
A26: 7 | B26: 37138008HM | C26: 2250102513-1.1 | D26: X2B038400BA1HA-HZ | E26: 3000 | F26: PCS | G26: 0.0385 | H26: USD | I26: =ROUND(E26*G26,2) -> 115.5 | J26: THAILAND | L26: HELE | M26: 境外品牌(其它) | N26: HSX221SA
A27: 8 | B27: 37138008HM | C27: 2250102986-3.1 | D27: X2B038400BA1HA-HZ | E27: 18000 | F27: PCS | G27: 0.0385 | H27: USD | I27: =ROUND(E27*G27,2) -> 693 | J27: THAILAND | L27: HELE | M27: 境外品牌(其它) | N27: HSX221SA
A28: 9 | B28: 3714062EHM | C28: 2250300844-11.1 | D28: X3S040000BF1HF-HZ | E28: 9000 | F28: PCS | G28: 0.031 | H28: USD | I28: =ROUND(E28*G28,2) -> 279 | J28: CHINA | L28: HELE | M28: 境外品牌(其它) | N28: HSX321S
A29: 10 | B29: 3714062EHM | C29: 2250302067-4.1 | D29: X3S040000BF1HF-HZ | E29: 3000 | F29: PCS | G29: 0.031 | H29: USD | I29: =ROUND(E29*G29,2) -> 93 | J29: CHINA | L29: HELE | M29: 境外品牌(其它) | N29: HSX321S
A30: 11 | B30: 3715060GHM | C30: 2250302882-5.1 | D30: X3S050000CJ1HA-HPZ | E30: 12000 | F30: PCS | G30: 0.0295 | H30: USD | I30: =ROUND(E30*G30,2) -> 354 | J30: CHINA | L30: HELE | M30: 境外品牌(其它) | N30: HSX321S
A31: 12 | B31: 3715060GHM | C31: 2250302882-5.1 | D31: X3S050000CJ1HA-HPZ | E31: 3000 | F31: PCS | G31: 0.0295 | H31: USD | I31: =ROUND(E31*G31,2) -> 88.5 | J31: CHINA | L31: HELE | M31: 境外品牌(其它) | N31: HSX321S
... A33: 14 | B33: 3720001PDS | C33: 2250702505-4.1 | D33: 7EG03200A01 | E33: 500 | F33: PCS | G33: 0.35 | H33: USD | I33: =ROUND(E33*G33,2) -> 175 | J33: JAPAN | L33: KDS | M33: 境外品牌(其它) | N33: DSB1612SDN
C34: TOTAL | E34: =SUM(E20:E33) -> 90500 | I34: =SUM(I20:I33) -> 3064

Sheet PACKING
A1: PACKING LIST
A3: Shipper/Exporter | F3: No & Date of Invoice
A4: HARMONY ELECTRONICS CORP. | F4: SH1-P80326
A5: No.39, Huadong Rd., Daliao Dist., Dafa Industrial Park, KAOHSIUNG 831, TAIWAN,CHINA | F5: 45883
A8: CONSIGNEE: | F8: Remarks:
A9: DWNET TECHNOLOGY (SUZHOU) CO., LTD.
A10: NO.8, TANGZHUANG ROAD, SUZHOU INDUSTRIAL PARK, JIANGSU, CHINA ZIP:215021
A13: Notify Party
A15: SAME AS CONSIGNEE
A17: Port of Departure | D17: Port of Arrival
A19: Carrier | D19: Sailing on/or About
A21: CTNS | B21: PO No. | C21: Part No. | D21: Description of Goods | F21: Quantity | G21: Unit | H21: Net WT | I21: Gross WT | J21: MEASUREMENT L*W*H(CM)
H22: KGS | I22: KGS
A23: 1 | B23: 2250600556-2.1 | C23: 3711260HHM | D23: X3S012000BC1HA-HU | F23: 3000 | G23: PCS | H23: 0.3 | I23: 0.5 | J23: 19*19*16
B24: 2250600556-2.1 | C24: 3711260HHM | D24: X3S012000BC1HA-HU | F24: 3000 | G24: PCS
A25: 1 | B25: 2250300844-10.1 | C25: 3712061GHM | D25: X3S025000BC1HA-HZ | F25: 12000 | G25: PCS | H25: 0.7 | I25: 0.9 | J25: 19*19*16
B26: 2250302067-3.1 | C26: 3712061GHM | D26: X3S025000BC1HA-HZ | E26: X3S025000BC1HA-HZ | F26: 3000 | G26: PCS
A27: 1 | B27: 2250501304-3.5 | C27: 3713260UHM | D27: X3S032000BC1HC-HZ | E27: X3S032000BC1HC-HZ | F27: 9000 | G27: PCS | H27: 0.4 | I27: 0.6 | J27: 19*19*16
A28: 1 | B28: 2250102340-3.1 | C28: 37138008HM | D28: X2B038400BA1HA-HZ | E28: X2B038400BA1HA-HZ | F28: 6000 | G28: PCS | H28: 0.7 | I28: 0.9 | J28: 19*19*16
B29: 2250102513-1.1 | C29: 37138008HM | D29: X2B038400BA1HA-HZ | E29: X2B038400BA1HA-HZ | F29: 3000 | G29: PCS
B30: 2250102986-3.1 | C30: 37138008HM | D30: X2B038400BA1HA-HZ | E30: X2B038400BA1HA-HZ | F30: 18000 | G30: PCS
A31: 1 | B31: 2250300844-11.1 | C31: 3714062EHM | D31: X3S040000BF1HF-HZ | E31: X3S040000BF1HF-HZ | F31: 9000 | G31: PCS | H31: 0.5 | I31: 0.7 | J31: 19*19*16
B32: 2250302067-4.1 | C32: 3714062EHM | D32: X3S040000BF1HF-HZ | E32: X3S040000BF1HF-HZ | F32: 3000 | G32: PCS
A33: 1 | B33: 2250302882-5.1 | C33: 3715060GHM | D33: X3S050000CJ1HA-HPZ | E33: X3S050000CJ1HA-HPZ | F33: 12000 | G33: PCS | H33: 0.9 | I33: 1.1 | J33: 19*19*16
B34: 2250302882-5.1 | C34: 3715060GHM | D34: X3S050000CJ1HA-HPZ | E34: X3S050000CJ1HA-HPZ | F34: 3000 | G34: PCS
B35: 2250400450-8.1 | C35: 3715060GHM | D35: X3S050000CJ1HA-HPZ | E35: X3S050000CJ1HA-HPZ | F35: 6000 | G35: PCS
A36: 1 | B36: 2250702505-4.1 | C36: 3720001PDS | D36: 7EG03200A01 | E36: 7EG03200A01 | F36: 500 | G36: PCS | H36: 0.1 | I36: 0.3 | J36: 19*19*16
A46: =SUM(A23:A45) -> 7 | E46: TOTAL | F46: =SUM(F23:F45) -> 90500 | H46: =SUM(H23:H45) -> 3.6 | I46: =SUM(I23:I45) -> 5
E47: 件数 | F47: =A46 -> 7
E48: 包装种类 | F48: 纸箱/托盘等
E49: 托盘材质 | F49: 再生木托/天然木托/塑胶托等

Sheet Sheet2
B1: 品名及料号 | C1: PO号 | D1: 型號 | E1: 供應商料號 | F1: 单位 | G1: 数量 | H1: 单价 | I1: 金额 | J1: 币制 | K1: 淨重 | L1: 原產國
B2: 3711260HHM | C2: 2250600556 | D2: HSX321S | E2: X3S012000BC1HA-HU | F2: PCS | G2: 3000 | H2: 0.031 | I2: =G2*H2 -> 93 | J2: USD | K2: 0.15 | L2: CHINA | M2: =VLOOKUP(L2,[1]国家代码!$A$1:$B$65536,2,0) -> 142
B3: 3711260HHM | C3: 2250600556 | D3: HSX321S | E3: X3S012000BC1HA-HU | F3: PCS | G3: 3000 | H3: 0.031 | I3: =G3*H3 -> 93 | J3: USD | K3: 0.15 | L3: CHINA | M3: =VLOOKUP(L3,[1]国家代码!$A$1:$B$65536,2,0) -> 142
B4: 3712061GHM | C4: 2250300844 | D4: HSX321S | E4: X3S025000BC1HA-HZ | F4: PCS | G4: 12000 | H4: 0.028 | I4: =G4*H4 -> 336 | J4: USD | K4: 0.56 | L4: CHINA | M4: =VLOOKUP(L4,[1]国家代码!$A$1:$B$65536,2,0) -> 142
B5: 3712061GHM | C5: 2250302067 | D5: HSX321S | E5: X3S025000BC1HA-HZ | F5: PCS | G5: 3000 | H5: 0.028 | I5: =G5*H5 -> 84 | J5: USD | K5: 0.14 | L5: CHINA | M5: =VLOOKUP(L5,[1]国家代码!$A$1:$B$65536,2,0) -> 142
B6: 3713260UHM | C6: 2250501304 | D6: HSX321S | E6: X3S032000BC1HC-HZ | F6: PCS | G6: 9000 | H6: 0.028 | I6: =G6*H6 -> 252 | J6: USD | K6: 0.4 | L6: CHINA | M6: =VLOOKUP(L6,[1]国家代码!$A$1:$B$65536,2,0) -> 142
B7: 37138008HM | C7: 2250102340 | D7: HSX221SA | E7: X2B038400BA1HA-HZ | F7: PCS | G7: 6000 | H7: 0.0385 | I7: =G7*H7 -> 231 | J7: USD | K7: 0.16 | L7: THAILAND | M7: =VLOOKUP(L7,[1]国家代码!$A$1:$B$65536,2,0) -> 136
B8: 37138008HM | C8: 2250102513 | D8: HSX221SA | E8: X2B038400BA1HA-HZ | F8: PCS | G8: 3000 | H8: 0.0385 | I8: =G8*H8 -> 115.5 | J8: USD | K8: 0.08 | L8: THAILAND | M8: =VLOOKUP(L8,[1]国家代码!$A$1:$B$65536,2,0) -> 136
B9: 37138008HM | C9: 2250102986 | D9: HSX221SA | E9: X2B038400BA1HA-HZ | F9: PCS | G9: 18000 | H9: 0.0385 | I9: =G9*H9 -> 693 | J9: USD | K9: 0.46 | L9: THAILAND | M9: =VLOOKUP(L9,[1]国家代码!$A$1:$B$65536,2,0) -> 136
B10: 3714062EHM | C10: 2250300844 | D10: HSX321S | E10: X3S040000BF1HF-HZ | F10: PCS | G10: 9000 | H10: 0.031 | I10: =G10*H10 -> 279 | J10: USD | K10: 0.37 | L10: CHINA | M10: =VLOOKUP(L10,[1]国家代码!$A$1:$B$65536,2,0) -> 142
B11: 3714062EHM | C11: 2250302067 | D11: HSX321S | E11: X3S040000BF1HF-HZ | F11: PCS | G11: 3000 | H11: 0.031 | I11: =G11*H11 -> 93 | J11: USD | K11: 0.13 | L11: CHINA | M11: =VLOOKUP(L11,[1]国家代码!$A$1:$B$65536,2,0) -> 142
B12: 3715060GHM | C12: 2250302882 | D12: HSX321S | E12: X3S050000CJ1HA-HPZ | F12: PCS | G12: 12000 | H12: 0.0295 | I12: =G12*H12 -> 354 | J12: USD | K12: 0.51 | L12: CHINA | M12: =VLOOKUP(L12,[1]国家代码!$A$1:$B$65536,2,0) -> 142
B13: 3715060GHM | C13: 2250302882 | D13: HSX321S | E13: X3S050000CJ1HA-HPZ | F13: PCS | G13: 3000 | H13: 0.0295 | I13: =G13*H13 -> 88.5 | J13: USD | K13: 0.13 | L13: CHINA | M13: =VLOOKUP(L13,[1]国家代码!$A$1:$B$65536,2,0) -> 142
... B15: 3720001PDS | C15: 2250702505 | D15: DSB1612SDN | E15: 7EG03200A01 | F15: PCS | G15: 500 | H15: 0.35 | I15: =G15*H15 -> 175 | J15: USD | K15: 0.1 | L15: JAPAN | M15: =VLOOKUP(L15,[1]国家代码!$A$1:$B$65536,2,0) -> 116

Sheet Sheet3
B1: 411
A2: 3711260HHM | B2: 2250600556 | C2: 3000 | D2: 0.031 | E2: USD | F2: 93 | G2: CHINA | H2: =VLOOKUP(G2,[1]国家代码!$A$1:$B$65536,2,0) -> 142 | I2: HELE | J2: 境外品牌(其它) | K2: HSX321S
A3: 3711260HHM | B3: 2250600556 | C3: 3000 | D3: 0.031 | E3: USD | F3: 93 | G3: CHINA | H3: =VLOOKUP(G3,[1]国家代码!$A$1:$B$65536,2,0) -> 142 | I3: HELE | J3: 境外品牌(其它) | K3: HSX321S
A4: 3712061GHM | B4: 2250300844 | C4: 12000 | D4: 0.028 | E4: USD | F4: 336 | G4: CHINA | H4: =VLOOKUP(G4,[1]国家代码!$A$1:$B$65536,2,0) -> 142 | I4: HELE | J4: 境外品牌(其它) | K4: HSX321S
A5: 3712061GHM | B5: 2250302067 | C5: 3000 | D5: 0.028 | E5: USD | F5: 84 | G5: CHINA | H5: =VLOOKUP(G5,[1]国家代码!$A$1:$B$65536,2,0) -> 142 | I5: HELE | J5: 境外品牌(其它) | K5: HSX321S
A6: 3713260UHM | B6: 2250501304 | C6: 9000 | D6: 0.028 | E6: USD | F6: 252 | G6: CHINA | H6: =VLOOKUP(G6,[1]国家代码!$A$1:$B$65536,2,0) -> 142 | I6: HELE | J6: 境外品牌(其它) | K6: HSX321S
A7: 37138008HM | B7: 2250102340 | C7: 6000 | D7: 0.0385 | E7: USD | F7: 231 | G7: THAILAND | H7: =VLOOKUP(G7,[1]国家代码!$A$1:$B$65536,2,0) -> 136 | I7: HELE | J7: 境外品牌(其它) | K7: HSX221SA
A8: 37138008HM | B8: 2250102513 | C8: 3000 | D8: 0.0385 | E8: USD | F8: 115.5 | G8: THAILAND | H8: =VLOOKUP(G8,[1]国家代码!$A$1:$B$65536,2,0) -> 136 | I8: HELE | J8: 境外品牌(其它) | K8: HSX221SA
A9: 37138008HM | B9: 2250102986 | C9: 18000 | D9: 0.0385 | E9: USD | F9: 693 | G9: THAILAND | H9: =VLOOKUP(G9,[1]国家代码!$A$1:$B$65536,2,0) -> 136 | I9: HELE | J9: 境外品牌(其它) | K9: HSX221SA
A10: 3714062EHM | B10: 2250300844 | C10: 9000 | D10: 0.031 | E10: USD | F10: 279 | G10: CHINA | H10: =VLOOKUP(G10,[1]国家代码!$A$1:$B$65536,2,0) -> 142 | I10: HELE | J10: 境外品牌(其它) | K10: HSX321S
A11: 3714062EHM | B11: 2250302067 | C11: 3000 | D11: 0.031 | E11: USD | F11: 93 | G11: CHINA | H11: =VLOOKUP(G11,[1]国家代码!$A$1:$B$65536,2,0) -> 142 | I11: HELE | J11: 境外品牌(其它) | K11: HSX321S
A12: 3715060GHM | B12: 2250302882 | C12: 12000 | D12: 0.0295 | E12: USD | F12: 354 | G12: CHINA | H12: =VLOOKUP(G12,[1]国家代码!$A$1:$B$65536,2,0) -> 142 | I12: HELE | J12: 境外品牌(其它) | K12: HSX321S
A13: 3715060GHM | B13: 2250302882 | C13: 3000 | D13: 0.0295 | E13: USD | F13: 88.5 | G13: CHINA | H13: =VLOOKUP(G13,[1]国家代码!$A$1:$B$65536,2,0) -> 142 | I13: HELE | J13: 境外品牌(其它) | K13: HSX321S
... A15: 3720001PDS | B15: 2250702505 | C15: 500 | D15: 0.35 | E15: USD | F15: 175 | G15: JAPAN | H15: =VLOOKUP(G15,[1]国家代码!$A$1:$B$65536,2,0) -> 116 | I15: KDS | J15: 境外品牌(其它) | K15: DSB1612SDN
