Workbook

Sheet INVOICE
A1: COMMERCIAL INVOICE
A2: Shipper/Exporter | E2: No. & Date of Invoice
A3: HeFei JingWeiTe Electronics Technology Co., Ltd 1st floor, standard workshop in Economic Development Zone, No. 3188 Yungu Road, Hefei Economic and Technological Development Zone, Anhui Province TEL :0086-551-63350092 FAX :0086-551-63350135 | E3: JWT283725081201
E4: 45881
A7: Bill To: | E7: Payment Term
A8: No. 8 Tangzhuang Road, Suzhou Industrial Park Jiangsu, China 中磊电子（苏州）有限公司 Sernet(Suzhou)Technologies Corporation
A11: Ship To: | E11: Trade Term
A12: No. 8 Tangzhuang Road, Suzhou Industrial Park Jiangsu, China 中磊电子（苏州）有限公司 Sernet(Suzhou)Technologies Corporation | E12: CIF
A14: Port of Loading | C14: Port of Discharge | E14: Remarks:
A17: Carrier | C17: Sailing on/or About
E18: 贸易国： | F18: CN
A19: ITEM | B19: Part No. | C19: PO No. | D19: Description of Goods Electric Crystal | E19: Quantity | F19: Unit | G19: Unit Price | H19: Currency | I19: Amount | J19: COO | K19: COD | L19: 品牌 | M19: 品牌类型 | N19: 型号 | O19: Net WT(KGS)
A20: 1 | B20: 3712563BJW | C20: 2250600398 | D20: 25.000MHz 20pF | E20: 27000 | F20: PCS | G20: 0.0215 | H20: USD | I20: =ROUND(E20*G20,2) -> 580.5 | J20: CHINA | L20: 晶威特 | M20: 境内自主品牌 | N20: 3225-4P | O20: =ROUND(E20/3000*0.16,2) -> 1.44
A21: 2 | B21: 3712563CJW | C21: 2250600152 | D21: 25.000MHz 20pF | E21: 9000 | F21: PCS | G21: 0.0215 | H21: USD | I21: =ROUND(E21*G21,2) -> 193.5 | J21: CHINA | L21: 晶威特 | M21: 境内自主品牌 | N21: 3225-4P | O21: =ROUND(E21/3000*0.16,2) -> 0.48
A22: 3 | B22: 37132618JW | C22: 2250601212 | D22: 32.000MHz 6pF | E22: 24000 | F22: PCS | G22: 0.07002 | H22: USD | I22: =ROUND(E22*G22,2) -> 1680.48 | J22: CHINA | L22: 晶威特 | M22: 境内自主品牌 | N22: 1612-4P | O22: =ROUND(E22/3000*0.16,2) -> 1.28
A23: 4 | B23: 3713800NJW | C23: 2250700288 | D23: 38.400MHz 10pF | E23: 3000 | F23: PCS | G23: 0.02952 | H23: USD | I23: =ROUND(E23*G23,2) -> 88.56 | J23: CHINA | L23: 晶威特 | M23: 境内自主品牌 | N23: 2520-4P | O23: =ROUND(E23/3000*0.16,2) -> 0.16
A24: 5 | B24: 3715060LJW | C24: 2250702624 | D24: 50.000MHz 10pF | E24: 6000 | F24: PCS | G24: 0.0225 | H24: USD | I24: =ROUND(E24*G24,2) -> 135 | J24: CHINA | L24: 晶威特 | M24: 境内自主品牌 | N24: 3225-4P | O24: =ROUND(E24/3000*0.16,2) -> 0.32
A25: 6 | B25: 3715060TJW | C25: 2250500125 | D25: 50.000MHz 10pF | E25: 30000 | F25: PCS | G25: 0.0225 | H25: USD | I25: =ROUND(E25*G25,2) -> 675 | J25: CHINA | L25: 晶威特 | M25: 境内自主品牌 | N25: 3225-4P | O25: =ROUND(E25/3000*0.16,2) -> 1.6
A26: 7 | B26: 3715060TJW | C26: 2250500125 | D26: 50.000MHz 10pF | E26: 21000 | F26: PCS | G26: 0.0225 | H26: USD | I26: =ROUND(E26*G26,2) -> 472.5 | J26: CHINA | L26: 晶威特 | M26: 境内自主品牌 | N26: 3225-4P | O26: =ROUND(E26/3000*0.16,2) -> 1.12
A27: 8 | B27: 37150615JW | C27: 2250601212 | D27: 50.000MHz 19pF | E27: 3000 | F27: PCS | G27: 0.0225 | H27: USD | I27: =ROUND(E27*G27,2) -> 67.5 | J27: CHINA | L27: 晶威特 | M27: 境内自主品牌 | N27: 3225-4P | O27: =ROUND(E27/3000*0.16,2) -> 0.16
A28: 9 | B28: 37154602JW | C28: 2230603028 | D28: 50.000MHz 19pF | E28: 3000 | F28: PCS | G28: 0.125 | H28: USD | I28: =ROUND(E28*G28,2) -> 375 | J28: CHINA | L28: 晶威特 | M28: 境内自主品牌 | N28: 2520-4P | O28: =ROUND(E28/3000*0.16,2) -> 0.16
C33: TOTAL | E33: =SUM(E20:E32) -> 126000 | I33: =SUM(I20:I32) -> 4268.04 | O33: =SUM(O20:O32) -> 6.72
H35: 报关行 | I35: 江苏众诚报关代理有限公司
H36: 申报地海关 | I36: 2358
H37: 关联备案号 | I37: 新帐册号T2358W000197（25.2.24开始）
H38: 运输方式 | I38: 保税港区

Sheet PACKING
A1: PACKING LIST
A3: Shipper/Exporter | F3: No & Date of Invoice
A4: =INVOICE!A3 -> HeFei JingWeiTe Electronics Technology Co., Ltd 1st floor, standard workshop in Economic Development Zone, No. 3188 Yungu Road, Hefei Economic and Technological Development Zone, Anhui Province TEL :0086-551-63350092 FAX :0086-551-63350135 | F4: =INVOICE!E3 -> JWT283725081201
F5: =INVOICE!E4 -> 45881
A8: Bill To: | F8: Remarks:
A9: =INVOICE!A8 -> No. 8 Tangzhuang Road, Suzhou Industrial Park Jiangsu, China 中磊电子（苏州）有限公司 Sernet(Suzhou)Technologies Corporation
A13: Ship To:
A14: =INVOICE!A12 -> No. 8 Tangzhuang Road, Suzhou Industrial Park Jiangsu, China 中磊电子（苏州）有限公司 Sernet(Suzhou)Technologies Corporation
A17: Port of Departure | D17: Port of Arrival
A19: Carrier | D19: Sailing on/or About
A21: CTNS | B21: PO No. | C21: Part No. | D21: Description of Goods | F21: Quantity | G21: Unit | H21: Net WT | I21: Gross WT | J21: MEASUREMENT L*W*H(CM)
H22: KGS | I22: KGS
A23: 1 | B23: 2250600398 | C23: 3712563BJW | D23: 25.000MHz 20pF | F23: 27000 | G23: PCS | H23: =F23/3000*0.16 -> 1.44 | I23: =F23/3000*0.2 -> 1.8 | J23: 19.5*12*20
A24: 2 | B24: 2250600152 | C24: 3712563CJW | D24: 25.000MHz 20pF | F24: 9000 | G24: PCS | H24: =F24/3000*0.16 -> 0.48 | I24: =F24/3000*0.2 -> 0.6 | J24: 19.5*12*20
A25: 3 | B25: 2250601212 | C25: 37132618JW | D25: 32.000MHz 6pF | F25: 24000 | G25: PCS | H25: =F25/3000*0.16 -> 1.28 | I25: =F25/3000*0.2 -> 1.6 | J25: 19.5*12*20
A26: 4 | B26: 2250700288 | C26: 3713800NJW | D26: 38.400MHz 10pF | F26: 3000 | G26: PCS | H26: =F26/3000*0.16 -> 0.16 | I26: =F26/3000*0.2 -> 0.2 | J26: 19.5*12*20
A27: 5 | B27: 2250702624 | C27: 3715060LJW | D27: 50.000MHz 10pF | F27: 6000 | G27: PCS | H27: =F27/3000*0.16 -> 0.32 | I27: =F27/3000*0.2 -> 0.4 | J27: 19.5*12*20
A28: 6 | B28: 2250500125 | C28: 3715060TJW | D28: 50.000MHz 10pF | F28: 30000 | G28: PCS | H28: =F28/3000*0.16 -> 1.6 | I28: =F28/3000*0.2 -> 2 | J28: 19.5*12*20
A29: 7 | B29: 2250500125 | C29: 3715060TJW | D29: 50.000MHz 10pF | F29: 21000 | G29: PCS | H29: =F29/3000*0.16 -> 1.12 | I29: =F29/3000*0.2 -> 1.4 | J29: 19.5*12*20
A30: 8 | B30: 2250601212 | C30: 37150615JW | D30: 50.000MHz 19pF | F30: 3000 | G30: PCS | H30: =F30/3000*0.16 -> 0.16 | I30: =F30/3000*0.2 -> 0.2 | J30: 19.5*12*20
A31: 9 | B31: 2230603028 | C31: 37154602JW | D31: 50.000MHz 19pF | F31: 3000 | G31: PCS | H31: =F31/3000*0.16 -> 0.16 | I31: =F31/3000*0.2 -> 0.2 | J31: 19.5*12*20
A37: 9 | E37: TOTAL | F37: =SUM(F23:F36) -> 126000 | H37: =SUM(H23:H36) -> 6.72 | I37: =SUM(I23:I36) -> 8.4 | J37: 0.04m³
E38: 件数 | F38: 9
E39: 包装种类 | F39: 纸箱
